src/zerodetect.v
`timescale 1ns/10ps
// zerodetect.v — asserts y=1 when all bits of a are zero
module zerodetect (a, y);
    input  [7:0] a;
    output       y;

    assign y = (a == 8'b0);
endmodule

sim/tb_zerodetect.v
`timescale 1ns/10ps
// tb_zerodetect.v — Self-checking testbench for zerodetect.v
// Delays scaled for SimVision waveform visibility

module tb_zerodetect;

    reg  [7:0] a;
    wire       y;
    integer    errors;

    zerodetect dut (.a(a), .y(y));

    // ---- Waveform dump ----
    initial begin
        $shm_open("dump_zerodetect.shm");
        $shm_probe("AS");
    end

    // ---- Clock: 100ns period ----
    reg clk;
    initial clk = 0;
    always #50 clk = ~clk;

    task check;
        input [7:0] in_a;
        input       expected;
        input [255:0] name;
        begin
            @(negedge clk);
            a = in_a;
            @(posedge clk); #5;
            if (y === expected)
                $display("PASS | %-20s | a=0x%02h (%08b) | y=%0b",
                         name, in_a, in_a, y);
            else begin
                $display("FAIL | %-20s | a=0x%02h (%08b) | y=%0b (exp %0b)",
                         name, in_a, in_a, y, expected);
                errors = errors + 1;
            end
        end
    endtask

    initial begin
        errors = 0;
        a      = 8'hFF;   // start non-zero so first transition is visible

        @(posedge clk);
        @(posedge clk);

        $display("\n=== ZeroDetect Testbench ===");

        check(8'h00, 1, "zero_all_zeros");
        check(8'h01, 0, "nonzero_LSB");
        check(8'hFF, 0, "nonzero_all_ones");
        check(8'h80, 0, "nonzero_MSB_only");
        check(8'h00, 1, "zero_again");
        check(8'hAA, 0, "nonzero_AA");
        check(8'h55, 0, "nonzero_55");
        check(8'h0F, 0, "nonzero_0F");
        check(8'hF0, 0, "nonzero_F0");
        check(8'h00, 1, "zero_final");

        repeat(5) @(posedge clk);

        $display("\n=== ZeroDetect: %0d error(s) ===", errors);
        if (errors == 0) $display("ALL ZERODETECT TESTS PASSED");
        else             $display("SOME ZERODETECT TESTS FAILED");
        $finish;
    end

endmodule

dump_zerodetect.vcd
$date
    Apr 14, 2026  11:05:06
$end
$version
    TOOL:	xmsim(64)	17.10-s001
$end
$timescale
    10 ps
$end

$scope module tb_zerodetect $end
$var reg       8 !    a [7:0] $end
$var wire      1 "    y  $end
$var integer  32 #    errors $end
$var reg       1 $    clk $end

$scope module dut $end
$var wire      8 %    a [7:0] $end
$var wire      1 "    y  $end
$upscope $end


$scope task check $end
$var reg       8 &    in_a [7:0] $end
$var reg       1 '    expected $end
$var reg      256 (    name [255:0] $end
$upscope $end

$upscope $end

$enddefinitions $end
$dumpvars
b11111111 !
0"
b0 #
0$
b11111111 %
bx &
x'
bx (
$end
#5000
1$
#10000
0$
#15000
1$
b0 &
1'
b111101001100101011100100110111101011111011000010110110001101100010111110111101001100101011100100110111101110011 (
#20000
0$
b0 !
b0 %
1"
#25000
1$
#25500
b1 &
0'
b110111001101111011011100111101001100101011100100110111101011111010011000101001101000010 (
#30000
0$
b1 !
b1 %
0"
#35000
1$
#35500
b11111111 &
b1101110011011110110111001111010011001010111001001101111010111110110000101101100011011000101111101101111011011100110010101110011 (
#40000
0$
b11111111 !
b11111111 %
#45000
1$
#45500
b10000000 &
b1101110011011110110111001111010011001010111001001101111010111110100110101010011010000100101111101101111011011100110110001111001 (
#50000
0$
b10000000 !
b10000000 %
#55000
1$
#55500
b0 &
1'
b1111010011001010111001001101111010111110110000101100111011000010110100101101110 (
#60000
0$
b0 !
b0 %
1"
#65000
1$
#65500
b10101010 &
0'
b1101110011011110110111001111010011001010111001001101111010111110100000101000001 (
#70000
0$
b10101010 !
b10101010 %
0"
#75000
1$
#75500
b1010101 &
b1101110011011110110111001111010011001010111001001101111010111110011010100110101 (
#80000
0$
b1010101 !
b1010101 %
#85000
1$
#85500
b1111 &
b1101110011011110110111001111010011001010111001001101111010111110011000001000110 (
#90000
0$
b1111 !
b1111 %
#95000
1$
#95500
b11110000 &
b1101110011011110110111001111010011001010111001001101111010111110100011000110000 (
#100000
0$
b11110000 !
b11110000 %
#105000
1$
#105500
b0 &
1'
b1111010011001010111001001101111010111110110011001101001011011100110000101101100 (
#110000
0$
b0 !
b0 %
1"
