src/mux23.v
`timescale 1ns/10ps
// mux23.v — 3-bit 2-to-1 multiplexer (for register address selection)
module mux23 (d0, d1, s, y);
    input        s;
    input  [2:0] d0, d1;
    output [2:0] y;

    assign y = s ? d1 : d0;
endmodule

src/mux4.v
`timescale 1ns/10ps
// mux4.v — 8-bit 4-to-1 multiplexer
module mux4 (d0, d1, d2, d3, s, y);
    input  [1:0] s;
    input  [7:0] d0, d1, d2, d3;
    output reg [7:0] y;

    always @(*) begin
        case (s)
            2'b00: y = d0;
            2'b01: y = d1;
            2'b10: y = d2;
            2'b11: y = d3;
            default: y = 8'b0;
        endcase
    end
endmodule

src/mux2.v
`timescale 1ns/10ps
// mux2.v — 8-bit 2-to-1 multiplexer
module mux2 (d0, d1, s, y);
    input        s;
    input  [7:0] d0, d1;
    output [7:0] y;

    assign y = s ? d1 : d0;
endmodule

sim/tb_muxes.v
`timescale 1ns/10ps
// tb_muxes.v — Self-checking testbench for mux2.v, mux4.v, mux23.v
// Delays scaled for SimVision waveform visibility

module tb_muxes;

    // mux2
    reg        s2;
    reg  [7:0] d0_2, d1_2;
    wire [7:0] y2;

    // mux4
    reg  [1:0] s4;
    reg  [7:0] d0_4, d1_4, d2_4, d3_4;
    wire [7:0] y4;

    // mux23
    reg        s23;
    reg  [2:0] d0_23, d1_23;
    wire [2:0] y23;

    integer errors;

    mux2  dut0 (.d0(d0_2),  .d1(d1_2),  .s(s2),  .y(y2));
    mux4  dut1 (.d0(d0_4),  .d1(d1_4),  .d2(d2_4), .d3(d3_4), .s(s4), .y(y4));
    mux23 dut2 (.d0(d0_23), .d1(d1_23), .s(s23), .y(y23));

    // ---- Waveform dump ----
    initial begin
        $shm_open("dump_muxes.shm");
        $shm_probe("AS");
    end

    // ---- Clock: 100ns period ----
    reg clk;
    initial clk = 0;
    always #50 clk = ~clk;

    task check8;
        input [7:0] actual, expected;
        input [255:0] name;
        begin
            if (actual === expected)
                $display("PASS | %-28s = 0x%02h (%3d)", name, actual, actual);
            else begin
                $display("FAIL | %-28s = 0x%02h (exp 0x%02h)", name, actual, expected);
                errors = errors + 1;
            end
        end
    endtask

    task check3;
        input [2:0] actual, expected;
        input [255:0] name;
        begin
            if (actual === expected)
                $display("PASS | %-28s = %03b", name, actual);
            else begin
                $display("FAIL | %-28s = %03b (exp %03b)", name, actual, expected);
                errors = errors + 1;
            end
        end
    endtask

    initial begin
        errors  = 0;
        s2      = 0; d0_2   = 0;   d1_2   = 0;
        s4      = 0; d0_4   = 0;   d1_4   = 0; d2_4 = 0; d3_4 = 0;
        s23     = 0; d0_23  = 0;   d1_23  = 0;

        @(posedge clk);
        @(posedge clk);

        $display("\n=== Mux Testbench ===");

        // ---- mux2 ----
        $display("\n-- mux2 --");
        d0_2 = 8'd10; d1_2 = 8'd20;
        @(negedge clk); s2 = 0; @(posedge clk); #5; check8(y2, 8'd10,  "mux2 s=0->d0(10)");
        @(negedge clk); s2 = 1; @(posedge clk); #5; check8(y2, 8'd20,  "mux2 s=1->d1(20)");

        d0_2 = 8'hAA; d1_2 = 8'h55;
        @(negedge clk); s2 = 0; @(posedge clk); #5; check8(y2, 8'hAA,  "mux2 s=0->0xAA");
        @(negedge clk); s2 = 1; @(posedge clk); #5; check8(y2, 8'h55,  "mux2 s=1->0x55");

        // ---- mux4 ----
        $display("\n-- mux4 --");
        d0_4=8'd10; d1_4=8'd20; d2_4=8'd30; d3_4=8'd40;
        @(negedge clk); s4=2'b00; @(posedge clk); #5; check8(y4, 8'd10, "mux4 s=00->d0(10)");
        @(negedge clk); s4=2'b01; @(posedge clk); #5; check8(y4, 8'd20, "mux4 s=01->d1(20)");
        @(negedge clk); s4=2'b10; @(posedge clk); #5; check8(y4, 8'd30, "mux4 s=10->d2(30)");
        @(negedge clk); s4=2'b11; @(posedge clk); #5; check8(y4, 8'd40, "mux4 s=11->d3(40)");

        // ---- mux23 ----
        $display("\n-- mux23 --");
        d0_23 = 3'b101; d1_23 = 3'b010;
        @(negedge clk); s23=0; @(posedge clk); #5; check3(y23, 3'b101, "mux23 s=0->101");
        @(negedge clk); s23=1; @(posedge clk); #5; check3(y23, 3'b010, "mux23 s=1->010");

        d0_23 = 3'b000; d1_23 = 3'b111;
        @(negedge clk); s23=0; @(posedge clk); #5; check3(y23, 3'b000, "mux23 s=0->000");
        @(negedge clk); s23=1; @(posedge clk); #5; check3(y23, 3'b111, "mux23 s=1->111");

        repeat(5) @(posedge clk);

        $display("\n=== Muxes: %0d error(s) ===", errors);
        if (errors == 0) $display("ALL MUX TESTS PASSED");
        else             $display("SOME MUX TESTS FAILED");
        $finish;
    end

endmodule

dump_muxes.vcd
$date
    Apr 14, 2026  10:35:48
$end
$version
    TOOL:	xmsim(64)	17.10-s001
$end
$timescale
    10 ps
$end

$scope module tb_muxes $end
$var reg       1 !    s2 $end
$var reg       8 "    d0_2 [7:0] $end
$var reg       8 #    d1_2 [7:0] $end
$var wire      8 $    y2 [7:0] $end
$var reg       2 %    s4 [1:0] $end
$var reg       8 &    d0_4 [7:0] $end
$var reg       8 '    d1_4 [7:0] $end
$var reg       8 (    d2_4 [7:0] $end
$var reg       8 )    d3_4 [7:0] $end
$var wire      8 *    y4 [7:0] $end
$var reg       1 +    s23 $end
$var reg       3 ,    d0_23 [2:0] $end
$var reg       3 -    d1_23 [2:0] $end
$var wire      3 .    y23 [2:0] $end
$var integer  32 /    errors $end
$var reg       1 0    clk $end

$scope module dut0 $end
$var wire      1 1    s  $end
$var wire      8 2    d0 [7:0] $end
$var wire      8 3    d1 [7:0] $end
$var wire      8 $    y [7:0] $end
$upscope $end


$scope module dut1 $end
$var wire      2 4    s [1:0] $end
$var wire      8 5    d0 [7:0] $end
$var wire      8 6    d1 [7:0] $end
$var wire      8 7    d2 [7:0] $end
$var wire      8 8    d3 [7:0] $end
$var reg       8 9    y [7:0] $end
$upscope $end


$scope module dut2 $end
$var wire      1 :    s  $end
$var wire      3 ;    d0 [2:0] $end
$var wire      3 <    d1 [2:0] $end
$var wire      3 .    y [2:0] $end
$upscope $end


$scope task check8 $end
$var reg       8 =    actual [7:0] $end
$var reg       8 >    expected [7:0] $end
$var reg      256 ?    name [255:0] $end
$upscope $end


$scope task check3 $end
$var reg       3 @    actual [2:0] $end
$var reg       3 A    expected [2:0] $end
$var reg      256 B    name [255:0] $end
$upscope $end

$upscope $end

$enddefinitions $end
$dumpvars
0!
b0 "
b0 #
b0 $
b0 %
b0 &
b0 '
b0 (
b0 )
b0 *
0+
b0 ,
b0 -
b0 .
b0 /
00
01
b0 2
b0 3
b0 4
b0 5
b0 6
b0 7
b0 8
b0 9
0:
b0 ;
b0 <
bx =
bx >
bx ?
bx @
bx A
bx B
$end
#5000
10
#10000
00
#15000
10
b1010 "
b10100 #
b10100 3
b1010 2
b1010 $
#20000
00
#25000
10
#25500
b1010 =
b1010 >
b1101101011101010111100000110010001000000111001100111101001100000010110100111110011001000011000000101000001100010011000000101001 ?
#30000
00
1!
11
b10100 $
#35000
10
#35500
b10100 =
b10100 >
b1101101011101010111100000110010001000000111001100111101001100010010110100111110011001000011000100101000001100100011000000101001 ?
b10101010 "
b1010101 #
b1010101 3
b10101010 2
b1010101 $
#40000
00
0!
01
b10101010 $
#45000
10
#45500
b10101010 =
b10101010 >
b110110101110101011110000011001000100000011100110011110100110000001011010011111000110000011110000100000101000001 ?
#50000
00
1!
11
b1010101 $
#55000
10
#55500
b1010101 =
b1010101 >
b110110101110101011110000011001000100000011100110011110100110001001011010011111000110000011110000011010100110101 ?
b1010 &
b10100 '
b11110 (
b101000 )
b101000 8
b11110 7
b10100 6
b1010 5
b1010 9
b1010 *
#60000
00
#65000
10
#65500
b1010 =
b1010 >
b110110101110101011110000011010000100000011100110011110100110000001100000010110100111110011001000011000000101000001100010011000000101001 ?
#70000
00
b1 %
b1 4
b10100 9
b10100 *
#75000
10
#75500
b10100 =
b10100 >
b110110101110101011110000011010000100000011100110011110100110000001100010010110100111110011001000011000100101000001100100011000000101001 ?
#80000
00
b10 %
b10 4
b11110 9
b11110 *
#85000
10
#85500
b11110 =
b11110 >
b110110101110101011110000011010000100000011100110011110100110001001100000010110100111110011001000011001000101000001100110011000000101001 ?
#90000
00
b11 %
b11 4
b101000 9
b101000 *
#95000
10
#95500
b101000 =
b101000 >
b110110101110101011110000011010000100000011100110011110100110001001100010010110100111110011001000011001100101000001101000011000000101001 ?
b101 ,
b10 -
b10 <
b101 ;
b101 .
#100000
00
#105000
10
#105500
b101 @
b101 A
b110110101110101011110000011001000110011001000000111001100111101001100000010110100111110001100010011000000110001 B
#110000
00
1+
1:
b10 .
#115000
10
#115500
b10 @
b10 A
b110110101110101011110000011001000110011001000000111001100111101001100010010110100111110001100000011000100110000 B
b0 ,
b111 -
b111 <
b0 ;
b111 .
#120000
00
0+
0:
b0 .
#125000
10
#125500
b0 @
b0 A
b110110101110101011110000011001000110011001000000111001100111101001100000010110100111110001100000011000000110000 B
#130000
00
1+
1:
b111 .
#135000
10
#135500
b111 @
b111 A
b110110101110101011110000011001000110011001000000111001100111101001100010010110100111110001100010011000100110001 B
